setup.cfg
setup.py
django_docker.egg-info/PKG-INFO
django_docker.egg-info/SOURCES.txt
django_docker.egg-info/dependency_links.txt
django_docker.egg-info/top_level.txt
docker/__init__.py
docker/admin.py
docker/apps.py
docker/models.py
docker/tests.py
docker/views.py
docker/management/__init__.py
docker/management/commands/__init__.py
docker/management/commands/docker_all.py
docker/management/commands/docker_build.py
docker/management/commands/docker_run.py
docker/management/commands/dockerfile.py
docker/templates/Dockerfile_apache2_wsgi.tpl
docker/templates/Dockerfile_python2.tpl
docker/templates/__init__.py
docker/templates/sites-apache2-nossl.tpl