Metadata-Version: 1.0
Name: django-docker
Version: 0.1
Summary: Module to create django docker based on your project
Home-page: https://github.com/plutec/django-docker
Author: Antonio Sanchez
Author-email: asanchez@plutec.net
License: Apache Version 2
Keywords: docker,docker-ce,django,apache2,wsgi,gunicorn,nginx
Platform: UNKNOWN
